ikuntime/__init__.py
KunTimeChange-11.5.dist-info/METADATA
KunTimeChange-11.5.dist-info/WHEEL
KunTimeChange-11.5.dist-info/top_level.txt
KunTimeChange-11.5.dist-info/RECORD
