Metadata-Version: 2.1
Name: KunTimeChange
Version: 11.5
Summary: A brief description of your package
Home-page: https://github.com/ziyin-wang/ikuntime
Author: W0518
Author-email: 2647346053@qq.com
License: MIT
Keywords: sample setuptools development
